RTL/timer_module.v
module timer (

    input  wire clk,
    input  wire rst,

    input  wire [2:0] current_state,

    output reg timer_done

);

    //=========================================
    // Timer Values
    //=========================================

    parameter GREEN_TIME  = 5;
    parameter YELLOW_TIME = 2;

    //=========================================
    // State Definitions
    //=========================================

    parameter S0 = 3'b000;
    parameter S1 = 3'b001;
    parameter S2 = 3'b010;
    parameter S3 = 3'b011;
    parameter S4 = 3'b100;
    parameter S5 = 3'b101;

    //=========================================
    // Counter
    //=========================================

    reg [3:0] count;
    reg [3:0] max_count;

    //=========================================
    // Select Timer Duration
    //=========================================

    always @(*)
    begin

        case(current_state)

            S0: max_count = GREEN_TIME;
            S1: max_count = YELLOW_TIME;

            S2: max_count = GREEN_TIME;
            S3: max_count = YELLOW_TIME;

            S4: max_count = GREEN_TIME;
            S5: max_count = GREEN_TIME;

            default:
                max_count = GREEN_TIME;

        endcase

    end

    //=========================================
    // Timer Counter
    //=========================================

    always @(posedge clk or posedge rst)
    begin

        if(rst)
        begin
            count <= 0;
            timer_done <= 0;
        end

        else
        begin

            if(count == max_count-1)
            begin
                count <= 0;
                timer_done <= 1;
            end

            else
            begin
                count <= count + 1;
                timer_done <= 0;
            end

        end

    end

endmodule

RTL/traffic_fsm.v
module traffic_fsm (

    input wire clk,
    input wire rst,

    input wire timer_done,

    input wire emergency_ns,
    input wire emergency_ew,

    output reg ns_red,
    output reg ns_yellow,
    output reg ns_green,

    output reg ew_red,
    output reg ew_yellow,
    output reg ew_green,

    output wire [2:0] state

);

    //======================================================
    // State Definitions
    //======================================================

    parameter S0 = 3'b000;   // NS Green, EW Red
    parameter S1 = 3'b001;   // NS Yellow, EW Red
    parameter S2 = 3'b010;   // NS Red, EW Green
    parameter S3 = 3'b011;   // NS Red, EW Yellow
    parameter S4 = 3'b100;   // Emergency NS
    parameter S5 = 3'b101;   // Emergency EW

    //======================================================
    // State Registers
    //======================================================

    reg [2:0] current_state;
    reg [2:0] next_state;

    // Make current state available to timer.v
    assign state = current_state;

    //======================================================
    // State Register (Sequential Logic)
    //======================================================

    always @(posedge clk or posedge rst)
    begin
        if (rst)
            current_state <= S0;
        else
            current_state <= next_state;
    end

    //======================================================
    // Next-State Logic
    //======================================================

    always @(*)
    begin

        // Default: Stay in current state
        next_state = current_state;

        case(current_state)

            //====================================
            // S0 : NS Green, EW Red
            //====================================
            S0:
            begin
                if (emergency_ns)
                    next_state = S4;
                else if (emergency_ew)
                    next_state = S5;
                else if (timer_done)
                    next_state = S1;
            end

            //====================================
            // S1 : NS Yellow, EW Red
            //====================================
            S1:
            begin
                if (emergency_ns)
                    next_state = S4;
                else if (emergency_ew)
                    next_state = S5;
                else if (timer_done)
                    next_state = S2;
            end

            //====================================
            // S2 : NS Red, EW Green
            //====================================
            S2:
            begin
                if (emergency_ns)
                    next_state = S4;
                else if (emergency_ew)
                    next_state = S5;
                else if (timer_done)
                    next_state = S3;
            end

            //====================================
            // S3 : NS Red, EW Yellow
            //====================================
            S3:
            begin
                if (emergency_ns)
                    next_state = S4;
                else if (emergency_ew)
                    next_state = S5;
                else if (timer_done)
                    next_state = S0;
            end

            //====================================
            // S4 : Emergency North-South
            //====================================
            S4:
            begin
                if (!emergency_ns)
                    next_state = S0;
            end

            //====================================
            // S5 : Emergency East-West
            //====================================
            S5:
            begin
                if (!emergency_ew)
                    next_state = S0;
            end

            //====================================
            // Safety Recovery
            //====================================
            default:
                next_state = S0;

        endcase

    end

    //======================================================
    // Output Logic
    //======================================================

    always @(*)
    begin

        // Default: Turn OFF all lights
        ns_red    = 0;
        ns_yellow = 0;
        ns_green  = 0;

        ew_red    = 0;
        ew_yellow = 0;
        ew_green  = 0;

        case(current_state)

            //====================================
            // S0 : NS Green, EW Red
            //====================================
            S0:
            begin
                ns_green = 1;
                ew_red   = 1;
            end

            //====================================
            // S1 : NS Yellow, EW Red
            //====================================
            S1:
            begin
                ns_yellow = 1;
                ew_red    = 1;
            end

            //====================================
            // S2 : NS Red, EW Green
            //====================================
            S2:
            begin
                ns_red   = 1;
                ew_green = 1;
            end

            //====================================
            // S3 : NS Red, EW Yellow
            //====================================
            S3:
            begin
                ns_red    = 1;
                ew_yellow = 1;
            end

            //====================================
            // S4 : Emergency North-South
            //====================================
            S4:
            begin
                ns_green = 1;
                ew_red   = 1;
            end

            //====================================
            // S5 : Emergency East-West
            //====================================
            S5:
            begin
                ns_red   = 1;
                ew_green = 1;
            end

            //====================================
            // Default Safe State
            //====================================
            default:
            begin
                ns_red = 1;
                ew_red = 1;
            end

        endcase

    end

endmodule

RTL/traffic_light_top.v
module top (

    input wire clk,
    input wire rst,

    input wire emergency_ns,
    input wire emergency_ew,

    output wire ns_red,
    output wire ns_yellow,
    output wire ns_green,

    output wire ew_red,
    output wire ew_yellow,
    output wire ew_green

);

    //==========================================
    // Internal Signals
    //==========================================

    wire timer_done;
    wire [2:0] state;

    //==========================================
    // Traffic FSM Instance
    //==========================================

    traffic_fsm FSM (

        .clk(clk),
        .rst(rst),

        .timer_done(timer_done),

        .emergency_ns(emergency_ns),
        .emergency_ew(emergency_ew),

        .ns_red(ns_red),
        .ns_yellow(ns_yellow),
        .ns_green(ns_green),

        .ew_red(ew_red),
        .ew_yellow(ew_yellow),
        .ew_green(ew_green),

        .state(state)

    );

    //==========================================
    // Timer Instance
    //==========================================

    timer TIMER (

        .clk(clk),
        .rst(rst),

        .current_state(state),

        .timer_done(timer_done)

    );

endmodule

TB/traffic_tb.v
`timescale 1ns/1ps

module traffic_tb;

    //=========================================================
    // Testbench Signals
    //=========================================================

    reg clk;
    reg rst;
    reg emergency_ns;
    reg emergency_ew;

    wire ns_red;
    wire ns_yellow;
    wire ns_green;

    wire ew_red;
    wire ew_yellow;
    wire ew_green;

    //=========================================================
    // Instantiate DUT (Device Under Test)
    //=========================================================

    top DUT (

        .clk(clk),
        .rst(rst),

        .emergency_ns(emergency_ns),
        .emergency_ew(emergency_ew),

        .ns_red(ns_red),
        .ns_yellow(ns_yellow),
        .ns_green(ns_green),

        .ew_red(ew_red),
        .ew_yellow(ew_yellow),
        .ew_green(ew_green)

    );

    //=========================================================
    // Waveform Generation
    //=========================================================

    initial
    begin
        $dumpfile("traffic.vcd");
        $dumpvars(0, traffic_tb);
    end

    //=========================================================
    // Console Monitor
    //=========================================================

    initial
    begin
        $monitor(
        "Time=%0t | NS(R,Y,G)=%b%b%b | EW(R,Y,G)=%b%b%b | EM_NS=%b EM_EW=%b",
        $time,
        ns_red, ns_yellow, ns_green,
        ew_red, ew_yellow, ew_green,
        emergency_ns, emergency_ew
        );
    end

    //=========================================================
    // Clock Generation
    //=========================================================

    initial
    begin
        clk = 0;
        forever #5 clk = ~clk;
    end

    //=========================================================
    // Test Cases
    //=========================================================

    initial
    begin

        $display("==========================================");
        $display(" Traffic Light Controller Simulation");
        $display("==========================================");

        //-------------------------------------
        // Initialize Inputs
        //-------------------------------------

        rst = 1;
        emergency_ns = 0;
        emergency_ew = 0;

        //-------------------------------------
        // Apply Reset
        //-------------------------------------

        #20;
        rst = 0;

        //-------------------------------------
        // Normal Operation
        //-------------------------------------

        #100;

        //-------------------------------------
        // Emergency on North-South
        //-------------------------------------

        $display("North-South Emergency Activated");

        emergency_ns = 1;

        #40;

        emergency_ns = 0;

        $display("North-South Emergency Cleared");

        //-------------------------------------
        // Normal Operation
        //-------------------------------------

        #100;

        //-------------------------------------
        // Emergency on East-West
        //-------------------------------------

        $display("East-West Emergency Activated");

        emergency_ew = 1;

        #40;

        emergency_ew = 0;

        $display("East-West Emergency Cleared");

        //-------------------------------------
        // Continue Simulation
        //-------------------------------------

        #100;

        $display("==========================================");
        $display("Simulation Completed Successfully");
        $display("==========================================");

        $finish;

    end

endmodule

WAVEFORMS/traffic.vcd
$date
	Wed Jul 29 23:02:09 2026
$end
$version
	Icarus Verilog
$end
$timescale
	1ps
$end
$scope module traffic_tb $end
$var wire 1 ! ns_yellow $end
$var wire 1 " ns_red $end
$var wire 1 # ns_green $end
$var wire 1 $ ew_yellow $end
$var wire 1 % ew_red $end
$var wire 1 & ew_green $end
$var reg 1 ' clk $end
$var reg 1 ( emergency_ew $end
$var reg 1 ) emergency_ns $end
$var reg 1 * rst $end
$scope module DUT $end
$var wire 1 ' clk $end
$var wire 1 ( emergency_ew $end
$var wire 1 ) emergency_ns $end
$var wire 1 * rst $end
$var wire 1 + timer_done $end
$var wire 3 , state [2:0] $end
$var wire 1 ! ns_yellow $end
$var wire 1 " ns_red $end
$var wire 1 # ns_green $end
$var wire 1 $ ew_yellow $end
$var wire 1 % ew_red $end
$var wire 1 & ew_green $end
$scope module FSM $end
$var wire 1 ' clk $end
$var wire 1 ( emergency_ew $end
$var wire 1 ) emergency_ns $end
$var wire 1 * rst $end
$var wire 3 - state [2:0] $end
$var wire 1 + timer_done $end
$var parameter 3 . S0 $end
$var parameter 3 / S1 $end
$var parameter 3 0 S2 $end
$var parameter 3 1 S3 $end
$var parameter 3 2 S4 $end
$var parameter 3 3 S5 $end
$var reg 3 4 current_state [2:0] $end
$var reg 1 & ew_green $end
$var reg 1 % ew_red $end
$var reg 1 $ ew_yellow $end
$var reg 3 5 next_state [2:0] $end
$var reg 1 # ns_green $end
$var reg 1 " ns_red $end
$var reg 1 ! ns_yellow $end
$upscope $end
$scope module TIMER $end
$var wire 1 ' clk $end
$var wire 3 6 current_state [2:0] $end
$var wire 1 * rst $end
$var parameter 32 7 GREEN_TIME $end
$var parameter 3 8 S0 $end
$var parameter 3 9 S1 $end
$var parameter 3 : S2 $end
$var parameter 3 ; S3 $end
$var parameter 3 < S4 $end
$var parameter 3 = S5 $end
$var parameter 32 > YELLOW_TIME $end
$var reg 4 ? count [3:0] $end
$var reg 4 @ max_count [3:0] $end
$var reg 1 + timer_done $end
$upscope $end
$upscope $end
$upscope $end
$enddefinitions $end
$comment Show the parameter values. $end
$dumpall
b10 >
b101 =
b100 <
b11 ;
b10 :
b1 9
b0 8
b101 7
b101 3
b100 2
b11 1
b10 0
b1 /
b0 .
$end
#0
$dumpvars
b101 @
b0 ?
b0 6
b0 5
b0 4
b0 -
b0 ,
0+
1*
0)
0(
0'
0&
1%
0$
1#
0"
0!
$end
#5000
1'
#10000
0'
#15000
1'
#20000
0'
0*
#25000
b1 ?
1'
#30000
0'
#35000
b10 ?
1'
#40000
0'
#45000
b11 ?
1'
#50000
0'
#55000
b100 ?
1'
#60000
0'
#65000
b1 5
1+
b0 ?
1'
#70000
0'
#75000
1!
1%
0#
b10 @
b1 ,
b1 -
b1 6
b1 4
0+
b1 ?
1'
#80000
0'
#85000
b10 5
1+
b0 ?
1'
#90000
0'
#95000
1&
1"
0%
0!
b101 @
b10 ,
b10 -
b10 6
b10 4
0+
b1 ?
1'
#100000
0'
#105000
b10 ?
1'
#110000
0'
#115000
b11 ?
1'
#120000
b100 5
0'
1)
#125000
1%
1#
0&
0"
b100 ?
b100 ,
b100 -
b100 6
b100 4
1'
#130000
0'
#135000
1+
b0 ?
1'
#140000
0'
#145000
0+
b1 ?
1'
#150000
0'
#155000
b10 ?
1'
#160000
b0 5
0'
0)
#165000
1%
1#
b11 ?
b0 ,
b0 -
b0 6
b0 4
1'
#170000
0'
#175000
b100 ?
1'
#180000
0'
#185000
b1 5
1+
b0 ?
1'
#190000
0'
#195000
1!
1%
0#
b10 @
b1 ,
b1 -
b1 6
b1 4
0+
b1 ?
1'
#200000
0'
#205000
b10 5
1+
b0 ?
1'
#210000
0'
#215000
1&
1"
0%
0!
b101 @
b10 ,
b10 -
b10 6
b10 4
0+
b1 ?
1'
#220000
0'
#225000
b10 ?
1'
#230000
0'
#235000
b11 ?
1'
#240000
0'
#245000
b100 ?
1'
#250000
0'
#255000
b11 5
1+
b0 ?
1'
#260000
b101 5
0'
1(
#265000
1&
1"
0+
b1 ?
b101 ,
b101 -
b101 6
b101 4
1'
#270000
0'
#275000
b10 ?
1'
#280000
0'
#285000
b11 ?
1'
#290000
0'
#295000
b100 ?
1'
#300000
b0 5
0'
0(
#305000
1%
1#
0&
0"
b1 5
1+
b0 ?
b0 ,
b0 -
b0 6
b0 4
1'
#310000
0'
#315000
1!
1%
0#
b10 @
b1 ,
b1 -
b1 6
b1 4
0+
b1 ?
1'
#320000
0'
#325000
b10 5
1+
b0 ?
1'
#330000
0'
#335000
1&
1"
0%
0!
b101 @
b10 ,
b10 -
b10 6
b10 4
0+
b1 ?
1'
#340000
0'
#345000
b10 ?
1'
#350000
0'
#355000
b11 ?
1'
#360000
0'
#365000
b100 ?
1'
#370000
0'
#375000
b11 5
1+
b0 ?
1'
#380000
0'
#385000
1$
0&
1"
b10 @
0+
b1 ?
b11 ,
b11 -
b11 6
b11 4
1'
#390000
0'
#395000
b0 5
1+
b0 ?
1'
